image_extractor/__init__.py
image_extractor/actions.py
image_extractor/helpers.py
image_extractor/main.py
image_extractor/test_here.py
image_extractor/web_classes.py
web_image_extractor-0.1.5.dist-info/licenses/LICENSE
web_image_extractor-0.1.5.dist-info/METADATA
web_image_extractor-0.1.5.dist-info/WHEEL
web_image_extractor-0.1.5.dist-info/top_level.txt
web_image_extractor-0.1.5.dist-info/RECORD
