Metadata-Version: 2.4
Name: web-image-extractor
Version: 0.1.5
Summary: Lightweight, dependency-free webpage image scraper
Author: Daniel
License: MIT
Project-URL: Homepage, https://github.com/DanielOnGitHub17/image-extractor
Requires-Python: >=3.14
License-File: LICENSE
Dynamic: license-file
